knox/__init__.py
knox/__main__.py
knox/knox.py
knox/requirements.txt
knox/backend/__init__.py
knox/backend/store.py
knox/backend/store_engine.py
knox/backend/store_file.py
knox/backend/store_object.py
knox/backend/store_vault.py
knox/certificate/__init__.py
knox/certificate/cert.py
knox/config/__init__.py
knox/config/cli.py
knox/config/conf.py
knox-0.0.13.dist-info/AUTHORS.rst
knox-0.0.13.dist-info/LICENSE
knox-0.0.13.dist-info/METADATA
knox-0.0.13.dist-info/WHEEL
knox-0.0.13.dist-info/entry_points.txt
knox-0.0.13.dist-info/top_level.txt
knox-0.0.13.dist-info/RECORD
