Metadata-Version: 2.1
Name: knox
Version: 0.0.13
Summary: Certificate management utilities with Vault backend
Home-page: https://github.com/8x8cloud/knox
Author: Lance Johnson
Author-email: lance@8x8.com
License: Apache-2.0
Project-URL: Documentation, https://knox.readthedocs.io/
Project-URL: Changelog, https://knox.readthedocs.io/en/latest/changelog.html
Project-URL: Issue Tracker, https://github.com/8x8cloud/knox/issues
Keywords: vault,hashicorp,ssl,certificates
Platform: UNKNOWN
Classifier: Development Status :: 1 - Planning
Classifier: Intended Audience :: Developers
Classifier: License :: OSI Approved :: Apache Software License
Classifier: Operating System :: Unix
Classifier: Operating System :: POSIX
Classifier: Operating System :: Microsoft :: Windows
Classifier: Programming Language :: Python
Classifier: Programming Language :: Python :: 3.6
Classifier: Programming Language :: Python :: 3.7
Classifier: Programming Language :: Python :: 3.8
Classifier: Programming Language :: Python :: Implementation :: CPython
Classifier: Programming Language :: Python :: Implementation :: PyPy
Classifier: Topic :: Utilities
Classifier: Topic :: Security
Requires-Python: >=2.7, !=3.0.*, !=3.1.*, !=3.2.*, !=3.3.*, !=3.4.*
Requires-Dist: click
Requires-Dist: hvac
Requires-Dist: loguru
Requires-Dist: dynaconf
Requires-Dist: shortuuid
